Metadata-Version: 1.0
Name: django-logicaldelete
Version: 1.1b1.dev3
Summary: a base model that provides built in logical delete functionality
Home-page: http://github.com/paltman/django-logicaldelete
Author: Patrick Altman
Author-email: paltman@gmail.com
License: BSD
Platform: UNKNOWN
Classifier: Development Status :: 4 - Beta
Classifier: Environment :: Web Environment
Classifier: Intended Audience :: Developers
Classifier: License :: OSI Approved :: BSD License
Classifier: Operating System :: OS Independent
Classifier: Programming Language :: Python
Classifier: Framework :: Django
